placavehiculos_pkg/__init__.py
placavehiculos_pkg/__main__.py
placavehiculos_pkg/placavehiculos.py
placavehiculos_pkg/test_placavehiculos.py
placavehiculos_pkg_aquintero535-1.0.2.dist-info/LICENSE
placavehiculos_pkg_aquintero535-1.0.2.dist-info/METADATA
placavehiculos_pkg_aquintero535-1.0.2.dist-info/WHEEL
placavehiculos_pkg_aquintero535-1.0.2.dist-info/top_level.txt
placavehiculos_pkg_aquintero535-1.0.2.dist-info/RECORD
