Metadata-Version: 2.1
Name: placavehiculos-pkg-aquintero535
Version: 1.0.2
Summary: Paquete de aplicacion que verifica la placa de un vehiculo
Home-page: https://gitlab.com/progllladrian/placa-vehiculos
Author: Adrian Quintero
Author-email: adrianquintero61@gmail.com
License: UNKNOWN
Platform: UNKNOWN
Classifier: Programming Language :: Python :: 3
Classifier: License :: OSI Approved :: MIT License
Classifier: Operating System :: OS Independent
Requires-Python: >=3.6
